[{"date":"2022-02-10","dosen_kumulativ":167780037,"impf_quote_erst":0.76096,"impf_quote_voll":0.74757,"dosen_differenz_zum_vortag":249516},{"date":"2022-02-11","dosen_kumulativ":168005432,"impf_quote_erst":0.76117,"impf_quote_voll":0.74828,"dosen_differenz_zum_vortag":225395},{"date":"2022-02-12","dosen_kumulativ":168107389,"impf_quote_erst":0.76129,"impf_quote_voll":0.74872,"dosen_differenz_zum_vortag":101957},{"date":"2022-02-13","dosen_kumulativ":168139424,"impf_quote_erst":0.76133,"impf_quote_voll":0.74886,"dosen_differenz_zum_vortag":32035},{"date":"2022-02-14","dosen_kumulativ":168256113,"impf_quote_erst":0.76144,"impf_quote_voll":0.74922,"dosen_differenz_zum_vortag":116689},{"date":"2022-02-15","dosen_kumulativ":168447225,"impf_quote_erst":0.76162,"impf_quote_voll":0.74979,"dosen_differenz_zum_vortag":191112},{"date":"2022-02-16","dosen_kumulativ":168633400,"impf_quote_erst":0.76177,"impf_quote_voll":0.75032,"dosen_differenz_zum_vortag":186175},{"date":"2022-02-17","dosen_kumulativ":168818066,"impf_quote_erst":0.76193,"impf_quote_voll":0.75087,"dosen_differenz_zum_vortag":184666},{"date":"2022-02-18","dosen_kumulativ":168992936,"impf_quote_erst":0.76212,"impf_quote_voll":0.75145,"dosen_differenz_zum_vortag":174870},{"date":"2022-02-19","dosen_kumulativ":169062869,"impf_quote_erst":0.7622,"impf_quote_voll":0.75178,"dosen_differenz_zum_vortag":69933},{"date":"2022-02-20","dosen_kumulativ":169089431,"impf_quote_erst":0.76223,"impf_quote_voll":0.75189,"dosen_differenz_zum_vortag":26562},{"date":"2022-02-21","dosen_kumulativ":169196318,"impf_quote_erst":0.76235,"impf_quote_voll":0.75223,"dosen_differenz_zum_vortag":106887},{"date":"2022-02-22","dosen_kumulativ":169350283,"impf_quote_erst":0.76249,"impf_quote_voll":0.75269,"dosen_differenz_zum_vortag":153965},{"date":"2022-02-23","dosen_kumulativ":169498242,"impf_quote_erst":0.76261,"impf_quote_voll":0.7531,"dosen_differenz_zum_vortag":147959}]